Roppit/__init__.py
roppit-0.1.dist-info/LICENSE.txt
roppit-0.1.dist-info/METADATA
roppit-0.1.dist-info/WHEEL
roppit-0.1.dist-info/top_level.txt
roppit-0.1.dist-info/RECORD
