Metadata-Version: 2.1
Name: roppit
Version: 0.1
Summary: This is the first version
Author: Daniel Mc Carthy
Author-email: daniel.mccarthy@roppit.com
License-File: LICENSE.txt
